texoutparse.py
texoutparse-1.0.0.dist-info/LICENSE
texoutparse-1.0.0.dist-info/METADATA
texoutparse-1.0.0.dist-info/WHEEL
texoutparse-1.0.0.dist-info/top_level.txt
texoutparse-1.0.0.dist-info/RECORD
