Metadata-Version: 2.1
Name: texoutparse
Version: 1.0.0
Summary: Simple LaTeX log file parsing library.
Home-page: https://github.com/inakleinbottle/texoutparse
Author: Sam Morley
Author-email: sam@inakleinbottle.com
License: MIT
Platform: UNKNOWN
